AXI_MASTER/AXI_master.v
`timescale 1ns/1ps
module axi4_master (
    input  wire        ACLK,
    input  wire        ARESETn,

    // WRITE ADDRESS
    output reg [31:0]  AWADDR,
    output reg [7:0]   AWLEN,
    output reg         AWVALID,
    input  wire        AWREADY,

    // WRITE DATA
    output reg [31:0]  WDATA,
    output reg         WLAST,
    output reg         WVALID,
    input  wire        WREADY,

    // WRITE RESPONSE
    input  wire        BVALID,
    output reg         BREADY,

    // READ ADDRESS
    output reg [31:0]  ARADDR,
    output reg [7:0]   ARLEN,
    output reg         ARVALID,
    input  wire        ARREADY,

    // READ DATA
    input  wire [31:0] RDATA,
    input  wire        RLAST,
    input  wire        RVALID,
    output reg         RREADY
);

    integer i;

    initial begin
        AWVALID = 0; WVALID = 0; BREADY = 0;
        ARVALID = 0; RREADY = 0; WLAST = 0;

        wait(ARESETn);

        // ---------------- WRITE BURST ----------------
        #10;
        AWADDR  = 32'h0000_0000;
        AWLEN   = 3;        // 4 beats
        AWVALID = 1;

        wait(AWREADY);
        AWVALID = 0;

        for (i = 0; i <= AWLEN; i = i + 1) begin
            WDATA  = 32'h100 + i;
            WVALID = 1;
            WLAST  = (i == AWLEN);
            wait(WREADY);
            #10;
        end

        WVALID = 0;
        WLAST  = 0;

        BREADY = 1;
        wait(BVALID);
        BREADY = 0;

        // ---------------- READ BURST ----------------
        #20;
        ARADDR  = 32'h0000_0000;
        ARLEN   = 3;
        ARVALID = 1;
        RREADY  = 1;

        wait(ARREADY);
        ARVALID = 0;

        wait(RLAST);
        RREADY = 0;
    end
endmodule

AXI_MASTER/tb_axi_master.v
`timescale 1ns/1ps

module tb_axi4_master;

    reg ACLK;
    reg ARESETn;

    // AXI signals
    wire [31:0] AWADDR;
    wire [7:0]  AWLEN;
    wire        AWVALID;
    reg         AWREADY;

    wire [31:0] WDATA;
    wire        WLAST;
    wire        WVALID;
    reg         WREADY;

    reg         BVALID;
    wire        BREADY;

    wire [31:0] ARADDR;
    wire [7:0]  ARLEN;
    wire        ARVALID;
    reg         ARREADY;

    reg  [31:0] RDATA;
    reg         RLAST;
    reg         RVALID;
    wire        RREADY;

    // Clock
    always #5 ACLK = ~ACLK;

    // DUT
    axi4_master dut (
        .ACLK(ACLK),
        .ARESETn(ARESETn),

        .AWADDR(AWADDR),
        .AWLEN(AWLEN),
        .AWVALID(AWVALID),
        .AWREADY(AWREADY),

        .WDATA(WDATA),
        .WLAST(WLAST),
        .WVALID(WVALID),
        .WREADY(WREADY),

        .BVALID(BVALID),
        .BREADY(BREADY),

        .ARADDR(ARADDR),
        .ARLEN(ARLEN),
        .ARVALID(ARVALID),
        .ARREADY(ARREADY),

        .RDATA(RDATA),
        .RLAST(RLAST),
        .RVALID(RVALID),
        .RREADY(RREADY)
    );

    initial begin
        // GTKWave dump
        $dumpfile("axi4_master.vcd");
        $dumpvars(0, tb_axi4_master);

        // Init
        ACLK = 0;
        ARESETn = 0;
        AWREADY = 0; WREADY = 0;
        BVALID  = 0;
        ARREADY = 0;
        RVALID  = 0; RLAST = 0;
        RDATA   = 32'h0;

        #20 ARESETn = 1;

        // Dummy AXI Slave behavior
        forever begin
            #10;
            AWREADY = AWVALID;
            WREADY  = WVALID;

            if (WLAST && WVALID) begin
                BVALID = 1;
                #10 BVALID = 0;
            end

            ARREADY = ARVALID;

            if (RREADY) begin
                RVALID = 1;
                RDATA  = 32'hDEAD_BEEF;
                RLAST  = 1;
                #10;
                RVALID = 0;
                RLAST  = 0;
            end
        end
    end

    initial begin
        #500 $finish;
    end
endmodule

AXI_MASTER/AXI_MASTER.sim/sim_1/behav/xsim/axi4_master.vcd
$date
   Wed Jan  7 11:19:24 2026
$end

$version
  2025.2
  $dumpfile ("axi4_master.vcd") 
$end

$timescale
  1ps
$end

$scope module tb_axi4_master $end
$var reg 1 ! ACLK $end
$var reg 1 " ARESETn $end
$var wire 32 # AWADDR [31:0] $end
$var wire 8 $ AWLEN [7:0] $end
$var wire 1 % AWVALID $end
$var reg 1 & AWREADY $end
$var wire 32 ' WDATA [31:0] $end
$var wire 1 ( WLAST $end
$var wire 1 ) WVALID $end
$var reg 1 * WREADY $end
$var reg 1 + BVALID $end
$var wire 1 , BREADY $end
$var wire 32 - ARADDR [31:0] $end
$var wire 8 . ARLEN [7:0] $end
$var wire 1 / ARVALID $end
$var reg 1 0 ARREADY $end
$var reg 32 1 RDATA [31:0] $end
$var reg 1 2 RLAST $end
$var reg 1 3 RVALID $end
$var wire 1 4 RREADY $end
$scope module dut $end
$var wire 1 5 ACLK $end
$var wire 1 6 ARESETn $end
$var reg 32 7 AWADDR [31:0] $end
$var reg 8 8 AWLEN [7:0] $end
$var reg 1 9 AWVALID $end
$var wire 1 : AWREADY $end
$var reg 32 ; WDATA [31:0] $end
$var reg 1 < WLAST $end
$var reg 1 = WVALID $end
$var wire 1 > WREADY $end
$var wire 1 ? BVALID $end
$var reg 1 @ BREADY $end
$var reg 32 A ARADDR [31:0] $end
$var reg 8 B ARLEN [7:0] $end
$var reg 1 C ARVALID $end
$var wire 1 D ARREADY $end
$var wire 32 E RDATA [31:0] $end
$var wire 1 F RLAST $end
$var wire 1 G RVALID $end
$var reg 1 H RREADY $end
$var integer 32 I i [31:0] $end
$upscope $end
$upscope $end
$enddefinitions $end

#0
$dumpvars
0!
0"
bx #
bx $
0%
0&
bx '
0(
0)
0*
0+
0,
bx -
bx .
0/
00
b0 1
02
03
04
05
06
bx 7
bx 8
09
0:
bx ;
0<
0=
0>
0?
0@
bx A
bx B
0C
0D
b0 E
0F
0G
0H
bx I
$end

#5000
1!
15

#10000
0!
05

#15000
1!
15

#20000
0!
1"
05
16

#25000
1!
15

#30000
0!
b0 #
b11 $
1%
05
b0 7
b11 8
19

#35000
1!
15

#40000
0!
0%
1&
b100000000 '
1)
05
09
1:
b100000000 ;
1=
b0 I

#45000
1!
15

#50000
0!
0&
1*
05
0:
1>

#55000
1!
15

#60000
0!
b100000001 '
05
b100000001 ;
b1 I

#65000
1!
15

#70000
0!
b100000010 '
05
b100000010 ;
b10 I

#75000
1!
15

#80000
0!
b100000011 '
1(
05
b100000011 ;
1<
b11 I

#85000
1!
15

#90000
0!
0(
0)
1+
05
0<
0=
1?
0@
b100 I

#95000
1!
15

#100000
0!
0+
05
0?

#105000
1!
15

#110000
0!
0*
b0 -
b11 .
0/
10
b11011110101011011011111011101111 1
12
13
04
05
0>
b0 A
b11 B
0C
1D
b11011110101011011011111011101111 E
1F
1G
0H

#115000
1!
15

#120000
0!
02
03
05
0F
0G

#125000
1!
15

#130000
0!
00
05
0D

